libsonyapi/__init__.py
libsonyapi/actions.py
libsonyapi/camera.py
libsonyapi-1.0.dist-info/LICENSE
libsonyapi-1.0.dist-info/METADATA
libsonyapi-1.0.dist-info/WHEEL
libsonyapi-1.0.dist-info/top_level.txt
libsonyapi-1.0.dist-info/RECORD
