Metadata-Version: 2.1
Name: libsonyapi
Version: 1.0
Summary: Python binding for Sony Camera API
Home-page: https://github.com/petabite/libsonyapi
Author: Philip Zhang
Author-email: jmslca123@gmail.com
License: MIT
Platform: UNKNOWN
Classifier: Topic :: Multimedia :: Graphics :: Capture :: Digital Camera
Classifier: Intended Audience :: Developers
Classifier: Programming Language :: Python :: 3
Classifier: License :: OSI Approved :: MIT License
Classifier: Operating System :: OS Independent
Requires-Dist: requests
